[
  {
    "name": "theme_info",
    "theme_name": "Skeleton",
    "theme_version": "0.1.0",
    "theme_author": "Shopify",
    "theme_documentation_url": "https://help.shopify.com/manual/online-store/themes",
    "theme_support_url": "https://support.shopify.com/"
  },
  {
    "name": "t:general.typography",
    "settings": [
      {
        "type": "header",
        "content": "t:general.fonts"
      },
      {
        "type": "font_picker",
        "id": "type_primary_font",
        "default": "work_sans_n4",
        "label": "t:general.primary"
      },
      {
        "type": "select",
        "id": "font_combination",
        "label": "Font Combination",
        "options": [
          {
            "value": "inter",
            "label": "Inter (Modern & Clean)"
          },
          {
            "value": "playfair_source",
            "label": "Playfair Display + Source Sans Pro (Elegant)"
          },
          {
            "value": "poppins_roboto",
            "label": "Poppins + Roboto Mono (Lifestyle Brand)"
          },
          {
            "value": "poppins_open",
            "label": "Poppins + Open Sans (Friendly)"
          },
          {
            "value": "custom",
            "label": "Use Shopify Font Picker"
          }
        ],
        "default": "poppins_roboto",
        "info": "Choose a pre-configured Google Font combination or use custom fonts"
      },
      {
        "type": "range",
        "id": "heading_font_weight",
        "min": 400,
        "max": 900,
        "step": 100,
        "label": "Heading Font Weight",
        "default": 600
      },
      {
        "type": "range",
        "id": "body_font_weight",
        "min": 300,
        "max": 600,
        "step": 100,
        "label": "Body Font Weight",
        "default": 400
      }
    ]
  },
  {
    "name": "t:general.layout",
    "settings": [
      {
        "type": "select",
        "id": "max_page_width",
        "label": "t:labels.page_width",
        "options": [
          {
            "value": "90rem",
            "label": "t:options.page_width.narrow"
          },
          {
            "value": "110rem",
            "label": "t:options.page_width.wide"
          }
        ],
        "default": "90rem"
      },
      {
        "type": "range",
        "id": "min_page_margin",
        "min": 10,
        "max": 100,
        "step": 1,
        "unit": "px",
        "label": "t:labels.page_margin",
        "default": 20
      }
    ]
  },
  {
    "name": "t:general.colors",
    "settings": [
      {
        "type": "header",
        "content": "Basic Colors"
      },
      {
        "type": "color",
        "id": "background_color",
        "default": "#FFFFFF",
        "label": "t:labels.background"
      },
      {
        "type": "color",
        "id": "foreground_color",
        "default": "#333333",
        "label": "t:labels.foreground"
      },
      {
        "type": "header",
        "content": "Brand Colors"
      },
      {
        "type": "color",
        "id": "primary_color",
        "default": "#2563eb",
        "label": "Primary Color",
        "info": "Used for buttons, links, and key brand elements"
      },
      {
        "type": "color",
        "id": "secondary_color",
        "default": "#64748b",
        "label": "Secondary Color",
        "info": "Used for secondary buttons and accents"
      },
      {
        "type": "color",
        "id": "accent_color",
        "default": "#f59e0b",
        "label": "Accent Color",
        "info": "Used for highlights and call-to-action elements"
      },
      {
        "type": "header",
        "content": "Lifestyle Brand Colors"
      },
      {
        "type": "color",
        "id": "brand_indigo_deep",
        "default": "#1E1B4B",
        "label": "Deep Indigo",
        "info": "Primary brand color for backgrounds and headers"
      },
      {
        "type": "color",
        "id": "brand_coral_vibrant",
        "default": "#FF6B6B",
        "label": "Vibrant Coral",
        "info": "CTA color for buttons and attention-grabbing elements"
      },
      {
        "type": "color",
        "id": "brand_blue_electric",
        "default": "#4B5EAA",
        "label": "Electric Blue",
        "info": "Accent color for hover effects and secondary elements"
      },
      {
        "type": "color",
        "id": "brand_white_soft",
        "default": "#F5F5F5",
        "label": "Soft White",
        "info": "Background color for light sections and text"
      },
      {
        "type": "header",
        "content": "Interface"
      },
      {
        "type": "range",
        "id": "input_corner_radius",
        "min": 0,
        "max": 20,
        "step": 1,
        "unit": "px",
        "label": "t:labels.input_corner_radius",
        "default": 6
      },
      {
        "type": "range",
        "id": "button_corner_radius",
        "min": 0,
        "max": 20,
        "step": 1,
        "unit": "px",
        "label": "Button Corner Radius",
        "default": 6
      }
    ]
  }
]
